autolink/__init__.py
autolink/__main__.py
autolink/autolink.py
autolink/extension.py
autolink/tag_index.py
autolink_md-0.1.0.dist-info/licenses/LICENSE
autolink_md-0.1.0.dist-info/METADATA
autolink_md-0.1.0.dist-info/WHEEL
autolink_md-0.1.0.dist-info/entry_points.txt
autolink_md-0.1.0.dist-info/top_level.txt
autolink_md-0.1.0.dist-info/RECORD
