Metadata-Version: 2.4
Name: autolink_md
Version: 0.1.0
Summary: functions and classes to automaticly link Markdownfiles through headers and wikilinks
Author-email: Horst Grewe <kooperto.raihead@gmail.com>
License:                     GNU GENERAL PUBLIC LICENSE
Project-URL: Homepage, https://github.com/00BraiNdeaD00/autolink
Project-URL: Changelog, https://github.com/00BraiNdeaD00/autolink/releases
Project-URL: Bug Tracker, https://github.com/00BraiNdeaD00/autolink/issues
Classifier: Programming Language :: Python :: 3
Classifier: License :: OSI Approved :: GNU General Public License v3 (GPLv3)
Classifier: Operating System :: OS Independent
Requires-Python: >=3.12
License-File: LICENSE
Dynamic: license-file
